{"corpusName":"select","title":"string","author.name":"string","subject.value":"string","abstract":"string","abstract.raw":"string","articleId":"string","articleId.raw":"string","author.affiliations":"string","author.affiliations.raw":"string","author.name.raw":"string","categories.inist":"string","categories.inist.raw":"string","categories.scienceMetrix":"string","categories.scienceMetrix.raw":"string","categories.wos":"string","categories.wos.raw":"string","chapterId":"string","chapterId.raw":"string","copyrightDate":"date","doi":"string","doi.raw":"string","editor.affiliations":"string","editor.affiliations.raw":"string","editor.name":"string","editor.name.raw":"string","eisbn":"string","eisbn.raw":"string","eissn":"string","eissn.raw":"string","enrichments.type":"string","enrichments.type.raw":"string","enrichments.grobid.mimetype":"string","enrichments.grobid.mimetype.raw":"string","enrichments.grobid.original":"boolean","enrichments.hubMeta.mimetype":"string","enrichments.hubMeta.mimetype.raw":"string","enrichments.hubMeta.original":"boolean","enrichments.keyterm.mimetype":"string","enrichments.keyterm.mimetype.raw":"string","enrichments.keyterm.original":"boolean","enrichments.multicat.mimetype":"string","enrichments.multicat.mimetype.raw":"string","enrichments.multicat.original":"boolean","enrichments.nb.mimetype":"string","enrichments.nb.mimetype.raw":"string","enrichments.nb.original":"boolean","enrichments.nerd.mimetype":"string","enrichments.nerd.mimetype.raw":"string","enrichments.nerd.original":"boolean","enrichments.refBibs.mimetype":"string","enrichments.refBibs.mimetype.raw":"string","enrichments.refBibs.original":"boolean","enrichments.teeft.mimetype":"string","enrichments.teeft.mimetype.raw":"string","enrichments.teeft.original":"boolean","enrichments.unitex.mimetype":"string","enrichments.unitex.mimetype.raw":"string","enrichments.unitex.original":"boolean","erratumOf":"string","erratumOf.raw":"string","genre":"string","genre.raw":"string","keywords.keyterm":"string","keywords.keyterm.raw":"string","keywords.teeft":"string","keywords.teeft.raw":"string","language":"string","language.raw":"string","namedEntities.nerd":"string","namedEntities.nerd.raw":"string","namedEntities.unitex":"string","namedEntities.unitex.raw":"string","originalGenre":"string","originalGenre.raw":"string","pii":"string","pii.raw":"string","pmid":"string","pmid.raw":"string","publicationDate":"date","qualityIndicators.score":"double","qualityIndicators.pdfWordCount":"integer","qualityIndicators.pdfVersion":"string","qualityIndicators.pdfVersion.raw":"string","qualityIndicators.pdfCharCount":"integer","qualityIndicators.abstractWordCount":"integer","qualityIndicators.refBibsNative":"boolean","qualityIndicators.abstractCharCount":"integer","qualityIndicators.pdfPageCount":"integer","sici":"string","sici.raw":"string","subject.lang":"string","subject.lang.raw":"string","subject.value.raw":"string","title.raw":"string","host.author.affiliations":"string","host.author.affiliations.raw":"string","host.author.name":"string","host.author.name.raw":"string","host.bookId":"string","host.bookId.raw":"string","host.conference.name":"string","host.conference.name.raw":"string","host.copyrightDate":"date","host.doi":"string","host.doi.raw":"string","host.editor.affiliations":"string","host.editor.affiliations.raw":"string","host.editor.name":"string","host.editor.name.raw":"string","host.eisbn":"string","host.eisbn.raw":"string","host.eissn":"string","host.eissn.raw":"string","host.genre":"string","host.genre.raw":"string","host.issn":"string","host.issn.raw":"string","host.isbn":"string","host.isbn.raw":"string","host.issue":"string","host.issue.raw":"string","host.journalId":"string","host.journalId.raw":"string","host.language":"string","host.language.raw":"string","host.pages.first":"string","host.pages.first.raw":"string","host.pages.last":"string","host.pages.last.raw":"string","host.pages.total":"string","host.pages.total.raw":"string","host.pii":"string","host.pii.raw":"string","host.pmid":"string","host.pmid.raw":"string","host.publicationDate":"date","host.publisherId":"string","host.publisherId.raw":"string","host.sici":"string","host.sici.raw":"string","host.subject.lang":"string","host.subject.lang.raw":"string","host.subject.value":"string","host.subject.value.raw":"string","host.title":"string","host.title.raw":"string","host.volume":"string","host.volume.raw":"string","serie.author.affiliations":"string","serie.author.affiliations.raw":"string","serie.author.name":"string","serie.author.name.raw":"string","serie.conference.name":"string","serie.conference.name.raw":"string","serie.copyrightDate":"date","serie.doi":"string","serie.doi.raw":"string","serie.editor.affiliations":"string","serie.editor.affiliations.raw":"string","serie.editor.name":"string","serie.editor.name.raw":"string","serie.eisbn":"string","serie.eisbn.raw":"string","serie.eissn":"string","serie.eissn.raw":"string","serie.genre":"string","serie.genre.raw":"string","serie.issn":"string","serie.issn.raw":"string","serie.isbn":"string","serie.isbn.raw":"string","serie.issue":"string","serie.issue.raw":"string","serie.journalId":"string","serie.journalId.raw":"string","serie.language":"string","serie.language.raw":"string","serie.pages.first":"string","serie.pages.first.raw":"string","serie.pages.last":"string","serie.pages.last.raw":"string","serie.pages.total":"string","serie.pages.total.raw":"string","serie.pii":"string","serie.pii.raw":"string","serie.pmid":"string","serie.pmid.raw":"string","serie.publicationDate":"date","serie.sici":"string","serie.sici.raw":"string","serie.subject.lang":"string","serie.subject.lang.raw":"string","serie.subject.value":"string","serie.subject.value.raw":"string","serie.title":"string","serie.title.raw":"string","serie.volume":"string","serie.volume.raw":"string","refBibs.author.name":"string","refBibs.author.name.raw":"string","refBibs.doi":"string","refBibs.doi.raw":"string","refBibs.issn":"string","refBibs.issn.raw":"string","refBibs.isbn":"string","refBibs.isbn.raw":"string","refBibs.issue":"string","refBibs.issue.raw":"string","refBibs.publicationDate":"date","refBibs.title":"string","refBibs.title.raw":"string","refBibs.volume":"string","refBibs.volume.raw":"string","refBibs.host.author.affiliations":"string","refBibs.host.author.affiliations.raw":"string","refBibs.host.author.name":"string","refBibs.host.author.name.raw":"string","refBibs.host.doi":"string","refBibs.host.doi.raw":"string","refBibs.host.isbn":"string","refBibs.host.isbn.raw":"string","refBibs.host.issn":"string","refBibs.host.issn.raw":"string","refBibs.host.issue":"string","refBibs.host.issue.raw":"string","refBibs.host.pages.first":"string","refBibs.host.pages.first.raw":"string","refBibs.host.pages.last":"string","refBibs.host.pages.last.raw":"string","refBibs.host.publicationDate":"date","refBibs.host.title":"string","refBibs.host.title.raw":"string","refBibs.host.volume":"string","refBibs.host.volume.raw":"string","refBibs.serie.doi":"string","refBibs.serie.doi.raw":"string","refBibs.serie.isbn":"string","refBibs.serie.isbn.raw":"string","refBibs.serie.issn":"string","refBibs.serie.issn.raw":"string","refBibs.serie.issue":"string","refBibs.serie.issue.raw":"string","refBibs.serie.pages.first":"string","refBibs.serie.pages.first.raw":"string","refBibs.serie.pages.last":"string","refBibs.serie.pages.last.raw":"string","refBibs.serie.title":"string","refBibs.serie.title.raw":"string","refBibs.serie.volume":"string","refBibs.serie.volume.raw":"string"}